linecache_light
