Metadata-Version: 1.0
Name: linecache-light
Version: 0.1.3
Summary: A python package that can fast random access any lines in a large file without high memory cost.
Home-page: https://github.com/Yelrose/linecache_light
Author: Ching Kit Wong
Author-email: 270018958@qq.com
License: MIT
Keywords: linecache,random access
Platform: UNKNOWN
